<?xml version="1.0" encoding="UTF-8"?>
<Dictionaries>
  <Dictionary Language="ChineseSimplified">
    <String Key="Game.Name" Value="遥控小车大作战" />
    <String Key="Game.Description" Value="玩家昵称" />
    <String Key="Game.Website" Value="https://GameFramework.cn/" />
    <String Key="Game.Summary" Value="极其休闲的一款小游戏，场均游戏时间非常短，上手容易，画风简洁，适合全年龄段玩家。这是一个使用 Game Framework 游戏框架制作的游戏." />
    <String Key="Game.Introduction" Value="通过操控遥控小车来达成目标，赢得胜利。游戏时间1分30秒，玩家使用按键/虚拟摇杆操控小车，小车初始血量为90。在游戏过程中，玩家可以随意的收集场上道具。若小车触碰其他玩家则双方弹回，并同时受到25点伤害。" />
    <String Key="Menu.StartButton" Value="人机模式" />
    <String Key="Menu.SettingButton" Value="设置" />
    <String Key="Menu.AboutButton" Value="关于" />
    <String Key="Menu.QuitButton" Value="退出" />
    <String Key="Dialog.ConfirmButton" Value="确定" />
    <String Key="Dialog.CancelButton" Value="取消" />
    <String Key="Dialog.OtherButton" Value="" />
    <String Key="ForceUpdate.Title" Value="强制更新" />
    <String Key="ForceUpdate.Message" Value="当前游戏版本过旧，是否前往更新？" />
    <String Key="ForceUpdate.UpdateButton" Value="更新" />
    <String Key="ForceUpdate.QuitButton" Value="退出" />
    <String Key="AskQuitGame.Title" Value="确认退出" />
    <String Key="AskQuitGame.Message" Value="是否确认退出游戏？" />
    <String Key="Setting.Title" Value="设置" />
    <String Key="Setting.Music" Value="音乐" />
    <String Key="Setting.Sound" Value="音效" />
    <String Key="Setting.UISound" Value="界面音效" />
    <String Key="Setting.Language" Value="语言" />
    <String Key="Setting.LanguageTips" Value="更改语言需要重启游戏" />
  </Dictionary>
</Dictionaries>
